rc_django/VERSION
rc_django/__init__.py
rc_django/decorators.py
rc_django/middleware.py
rc_django/models.py
rc_django/urls.py
rc_django/templates/access_denied.html
rc_django/templates/cause_errors.html
rc_django/templates/customform.html
rc_django/templates/proxy.html
rc_django/templates/proxy_wrapper.html
rc_django/templates/customform/libcurrics/course.html
rc_django/templates/customform/libcurrics/default.html
rc_django/templates/customform/libcurrics/index.html
rc_django/templates/customform/libraries/index.html
rc_django/templates/proxy/gws/group_sws/v3/search.html
rc_django/templates/proxy/pws/identity/v2/entity.html
rc_django/templates/proxy/pws/identity/v2/person.html
rc_django/templates/proxy/sws/student/v5/college.html
rc_django/templates/proxy/sws/student/v5/course.html
rc_django/templates/proxy/sws/student/v5/curriculum.html
rc_django/templates/proxy/sws/student/v5/department.html
rc_django/templates/proxy/sws/student/v5/enrollment.html
rc_django/templates/proxy/sws/student/v5/person.html
rc_django/templates/proxy/sws/student/v5/registration.html
rc_django/templates/proxy/sws/student/v5/section.html
rc_django/templates/proxy/sws/student/v5/includes/changed_since_date.html
rc_django/templates/proxy/sws/student/v5/includes/college_abbreviation.html
rc_django/templates/proxy/sws/student/v5/includes/course.html
rc_django/templates/proxy/sws/student/v5/includes/department_abbreviation.html
rc_django/templates/proxy/sws/student/v5/includes/page_size.html
rc_django/templates/proxy/sws/student/v5/includes/reg_id.html
rc_django/templates/proxy/sws/student/v5/includes/section_id.html
rc_django/templates/proxy/sws/student/v5/includes/term.html
rc_django/templates/proxy/sws/student/v5/includes/transcriptable_course.html
rc_django/templates/proxy/sws/student/v5/includes/view_unpublished.html
rc_django/tests/__init__.py
rc_django/tests/test_models.py
rc_django/tests/test_views.py
rc_django/tests/performance/__init__.py
rc_django/tests/performance/test_delay.py
uw_restclients_django_utils-2.3.11.dist-info/licenses/LICENSE
uw_restclients_django_utils-2.3.11.dist-info/METADATA
uw_restclients_django_utils-2.3.11.dist-info/WHEEL
uw_restclients_django_utils-2.3.11.dist-info/top_level.txt
uw_restclients_django_utils-2.3.11.dist-info/RECORD
