Metadata-Version: 2.4
Name: UW-RestClients-Django-Utils
Version: 2.3.11
Summary: UW-RestClients-Django-Utils
Home-page: https://github.com/uw-it-aca/uw-restclients-django-utils
Author: UW-IT Student & Educational Technology Services
Author-email: aca-it@uw.edu
License: Apache License, Version 2.0
Classifier: Intended Audience :: Developers
Classifier: License :: OSI Approved :: Apache Software License
Classifier: Operating System :: OS Independent
Classifier: Programming Language :: Python
License-File: LICENSE
Requires-Dist: django
Requires-Dist: uw-restclients-core
Requires-Dist: django-userservice
Dynamic: author
Dynamic: author-email
Dynamic: classifier
Dynamic: description
Dynamic: home-page
Dynamic: license
Dynamic: license-file
Dynamic: requires-dist
Dynamic: summary
